Workbook

Sheet Read Me
A1: Coharts Seed: institutional investor pipeline
A3: Generated | B3: 2026-09-30
A4: Firms in this workbook | B4: 56
A5: Round parameters | B5: Institutional Seed, $6M target (valuation TBD with lead; ~26 months runway). POSITIONING UPDATE per Oct 2026 deck: Coharts = drug-development INFRASTRUCTURE, 'one record per program, from first assay to filing, with the models built in.' Foresight Base is the program record ($2K/program/month; Part 11 + ICH E6(R3) data management) with modules (PRISM, ATHENA, BEAM, CTS, iViz) switching on by stage. Applied AI, IaaS (never SaaS). Now also competes with the record/eTMF vaults (Veeva, Medidata Rave, Benchling), not only simulation tools, adding a THIRD investor door: enterprise / vertical-SaaS / dev-infrastructure. Validation is RETROSPECTIVE (LEAP Phase 2, bioavailability, failures re-run); NSCLC in PoC. Traction: Tempus POC (results for JPM Jan 2027), Synthon generics pilot complete (paid conversion $250K-$415K), PRISM with 2 pediatric hospitals (FDA grant filed/pending). A $6M seed favors seed-LEADING funds; most check sizes Unknown pending PitchBook; personal emails inferred unless marked Verified. None of these firms are in the HubSpot pipeline. CONFLICT FLAGGED: Radical Ventures holds Unlearn.AI (direct competitor). WARM-PATH NODES: Josh Seidenfeld (DLA Piper) = legal-partner intros (bumps on a16z/Lux/Basis Set/Bessemer, contingent on DLA); Johnny = BD / life-sciences venture-banking contact coordinating the intros. Other firms remain warm-path 1-2 pending named nodes.
A6: Prepared by | B6: Coharts
A8: How to use this workbook
A9: Pipeline | B9: One row per firm. Sort or filter on Fit score and Tier. Blue cells are inputs you can edit, black cells are calculated.
A10: Weights | B10: Change a weight or a tier threshold and every Fit score and Tier recalculates. Weights should total 100.
A11: Sources | B11: One row per claim, so any cell in Pipeline can be traced to the page that supports it.
A13: Scoring
A14: Method | B14: Six dimensions scored 0 to 5, weighted to a 0 to 100 Fit score, less a conflict penalty. Tier A at 70 and above, B from 50 to 69, C below 50.
A15: Conflict flag | B15: Set to 1 when the firm holds a company competing directly with Foresight CDI, iViz, or PRISM. The named company goes in Conflict detail.
A17: Evidence rules
A18: Unknown is a real value | B18: An empty or Unknown cell means no source supported the claim. It is not a gap to be filled in from inference.
A19: Every row is dated | B19: Fund sizes, partner rosters, and theses go stale. Re-verify before reusing a row in a later cycle.
A20: People | B20: Partner names and titles come from the firm's own site, a paid data record, or a dated press item. Nowhere else.

Sheet Pipeline
A1: Firm | B1: Firm type | C1: HQ | D1: Latest fund (size, vintage) | E1: Stage focus | F1: Typical check | G1: Leads seed? | H1: Already in pipeline? | I1: Life science evidence | J1: Applied AI evidence | K1: Closest portfolio comps | L1: Conflict flag (0/1) | M1: Conflict detail | N1: Contact name | O1: Contact title | P1: Warm path | Q1: Life science score (0-5) | R1: Applied AI score (0-5) | S1: Stage score (0-5) | T1: Check size score (0-5) | U1: Warm path score (0-5) | V1: Activity score (0-5) | W1: Fit score | X1: Tier | Y1: Status | Z1: Owner | AA1: Next action | AB1: Last verified (YYYY-MM-DD) | AC1: Source URLs | AD1: Notes
A2: Dimension Capital | B2: TechBio seed/early fund | C2: San Francisco / New York | D2: Fund III, $800M, closed Jul 2026 ($1.65B AUM) | E2: Seed and Series A, leads, life science x compute | F2: Unknown | G2: Yes | H2: No | I2: Purpose-built for the life science x compute/AI intersection. Co-led $30M seed in Chai Discovery (AI drug-design models, 2024). Multiple computational-bio holdings. | J2: Explicit thesis that science and compute are converging; partners publish on TechBio/AI. Portfolio is AI-native. | K2: Chai Discovery (AI drug design, not a direct Foresight competitor). | L2: 0 | M2: Unknown | N2: Zavain Dar | O2: Co-Founder and Managing Partner | P2: Plausible via a Chai Discovery founder or shared tech-bio operator; no named node confirmed yet. | Q2: 5 | R2: 5 | S2: 5 | T2: 0 | U2: 2 | V2: 5 | W2: =MAX(0,ROUND(Q2/5*Weights!$B$3+R2/5*Weights!$B$4+S2/5*Weights!$B$5+T2/5*Weights!$B$6+U2/5*Weights!$B$7+V2/5*Weights!$B$8-L2*Weights!$B$9,0)) -> 84 | X2: =IF(W2>=Weights!$B$12,"A",IF(W2>=Weights!$B$13,"B","C")) -> A | Y2: Not contacted | Z2: Nate | AA2: Map a named warm intro to Zavain Dar; confirm seed check band. | AB2: 2026-09-30 | AC2: https://techcrunch.com/2026/07/21/dimension-capitals-800m-third-fund-shows-the-intersection-of-science-and-compute-is-booming/; https://www.dimensioncap.com/ | AD2: Highest-fit fund. Contact email inferred/unverified; firm general inbox contact@dimensioncap.com is verified. Do not confuse with Florida 'Dimension Capital Management'.
A3: a16z Bio + Health | B3: Multistage platform, bio+health fund | C3: Menlo Park, CA | D3: Bio+Health funds active (size/vintage not re-verified) | E3: Seed to growth in AI-in-healthcare software; selective at seed | F3: Unknown | G3: Selective | H3: No | I3: Dedicated bio+health practice investing in AI-native healthcare/life-science software. Portfolio includes Hippocratic AI, Turquoise Health. | J3: Published AI-in-healthcare theses (2026); the broader a16z applied-AI franchise sits alongside. | K3: Hippocratic AI (clinical AI, not trial simulation). | L3: 0 | M3: Unknown | N3: Julie Yoo | O3: General Partner (alt: Jay Rughani, Partner) | P3: STRONG via DLA Piper (engaged counsel): partner Josh Seidenfeld personally led a16z's Prosper AI health-AI financing at DLA in 2026. Confirm the intro with Seidenfeld. | Q3: 5 | R3: 5 | S3: 4 | T3: 0 | U3: 4 | V3: 5 | W3: =MAX(0,ROUND(Q3/5*Weights!$B$3+R3/5*Weights!$B$4+S3/5*Weights!$B$5+T3/5*Weights!$B$6+U3/5*Weights!$B$7+V3/5*Weights!$B$8-L3*Weights!$B$9,0)) -> 84 | X3: =IF(W3>=Weights!$B$12,"A",IF(W3>=Weights!$B$13,"B","C")) -> A | Y3: Not contacted | Z3: Nate | AA3: Ask Josh Seidenfeld (DLA Piper) for a direct intro to the bio+health team. | AB3: 2026-09-30 | AC3: https://a16z.com/infinite-healthcare-whats-it-worth/; https://www.dlapiper.com/en-us/news/2026/06/dla-piper-advises-andreessen-horowitz-on-usd30-million-investment-in-prosper-ai | AD3: Warm path via DLA Piper counsel (Seidenfeld led an a16z health-AI deal); score contingent on DLA making the intro. Emails inferred/unverified: julie@a16z.com (~55%) or jyoo@a16z.com (~62%).
A4: Section 32 | B4: Frontier tech + healthcare fund | C4: San Diego / Bay Area | D4: Active (fund size/vintage not re-verified) | E4: Seed onward across healthcare/life-sciences and frontier tech | F4: Unknown | G4: Selective | H4: No | I4: Healthcare/dx/life-sciences core; portfolio includes Freenome and precision-medicine companies. MP ran Foundation Medicine. | J4: AI + healthcare/data across the portfolio; named focus with evidence. | K4: Freenome (dx/AI, not a direct Foresight competitor). | L4: 0 | M4: Unknown | N4: Michael Pellini, MD | O4: Managing Partner | P4: Intro via a Foundation Medicine or Freenome alumnus; no named node confirmed. | Q4: 5 | R4: 4 | S4: 4 | T4: 0 | U4: 2 | V4: 4 | W4: =MAX(0,ROUND(Q4/5*Weights!$B$3+R4/5*Weights!$B$4+S4/5*Weights!$B$5+T4/5*Weights!$B$6+U4/5*Weights!$B$7+V4/5*Weights!$B$8-L4*Weights!$B$9,0)) -> 74 | X4: =IF(W4>=Weights!$B$12,"A",IF(W4>=Weights!$B$13,"B","C")) -> A | Y4: Not contacted | Z4: Nate | AA4: Confirm a fresh 2025-26 deal to reference; find FMI/Freenome intro. | AB4: 2026-09-30 | AC4: https://www.crunchbase.com/person/michael-j-pellini; https://www.linkedin.com/in/michael-pellini-57a1b919/ | AD4: Email inferred/unverified: michael@section32.com (~72%). Domain is section32.com.
A5: Lux Capital | B5: Frontier science + tech fund | C5: New York / Menlo Park | D5: Active flagship (size/vintage not re-verified) | E5: Seed to early growth; frontier science and AI infra | F5: Unknown | G5: Yes | H5: No | I5: Frontier science + tech with a health/AI-infra bench. Shakir focuses on digital-health infrastructure and AI-health. | J5: Strong applied-AI and data-infra practice plus a published frontier-tech thesis; portfolio follows. | K5: None competing directly with Foresight/iViz identified. | L5: 0 | M5: Unknown | N5: Deena Shakir | O5: General Partner | P5: PLAUSIBLE via DLA Piper: SF partner Jonathan Axelrad represents Lux in financings; intro would hand off from Seidenfeld to Axelrad. Confirm with DLA. | Q5: 5 | R5: 5 | S5: 4 | T5: 0 | U5: 3 | V5: 4 | W5: =MAX(0,ROUND(Q5/5*Weights!$B$3+R5/5*Weights!$B$4+S5/5*Weights!$B$5+T5/5*Weights!$B$6+U5/5*Weights!$B$7+V5/5*Weights!$B$8-L5*Weights!$B$9,0)) -> 80 | X5: =IF(W5>=Weights!$B$12,"A",IF(W5>=Weights!$B$13,"B","C")) -> A | Y5: Not contacted | Z5: Nate | AA5: Ask DLA (Axelrad) about a Lux intro to Deena Shakir; verify email. | AB5: 2026-09-30 | AC5: https://www.luxcapital.com/people; https://www.dlapiper.com/en/people/a/jonathan-axelrad | AD5: Adam Goulburn is at Dimension, NOT Lux. Warm path via DLA partner Axelrad (represents Lux); contingent on the hand-off. Email inferred/unverified: deena.shakir@luxcapital.com (pattern first.last ~90%).
A6: Foresite Capital | B6: Healthcare + life-science infrastructure fund | C6: San Francisco, CA | D6: Fund VI, $900M, closed Jun 2024 | E6: Seed to growth; precision medicine and LS infrastructure | F6: Unknown | G6: Selective | H6: No | I6: Precision medicine + LS infrastructure; co-led ~$1B Xaira Therapeutics (Apr 2024). Foresite Labs incubates data-driven health companies. | J6: ML/genetics-native; Bajaj is a data-science MD/PhD (ex-Verily/Grail). More bio than pure applied-AI. | K6: Xaira (AI drug discovery, not clinical trial simulation). | L6: 0 | M6: Unknown | N6: Vik Bajaj, PhD | O6: Managing Director; Co-Founder/CEO Foresite Labs | P6: Foresite Labs network; no named node confirmed. | Q6: 5 | R6: 4 | S6: 3 | T6: 0 | U6: 2 | V6: 5 | W6: =MAX(0,ROUND(Q6/5*Weights!$B$3+R6/5*Weights!$B$4+S6/5*Weights!$B$5+T6/5*Weights!$B$6+U6/5*Weights!$B$7+V6/5*Weights!$B$8-L6*Weights!$B$9,0)) -> 72 | X6: =IF(W6>=Weights!$B$12,"A",IF(W6>=Weights!$B$13,"B","C")) -> A | Y6: Not contacted | Z6: Nate | AA6: Confirm email local-part (vik vs vikram); find Labs intro. | AB6: 2026-09-30 | AC6: https://www.biopharmadive.com/news/foresite-950-million-fund-vi-venture-capital/718617/; https://www.foresitecapital.com/ | AD6: Email inferred/unverified: vik.bajaj@foresitecapital.com (~68%); vik vs vikram ambiguous.
A7: Khosla Ventures | B7: Multistage, AI-forward fund | C7: Menlo Park, CA | D7: Active (size/vintage not re-verified) | E7: Seed to growth; AI-forward, seed-friendly | F7: Unknown | G7: Yes | H7: No | I7: Bio + healthcare investing with a physician-scientist partner; led $50M Series B in Rad AI (2024). | J7: AI-forward across the firm; deep applied-AI portfolio. | K7: Rad AI (radiology AI, not trial simulation). | L7: 0 | M7: Unknown | N7: Alex Morgan, MD/PhD | O7: Partner | P7: LinkedIn or portfolio founder; no named node confirmed. | Q7: 4 | R7: 5 | S7: 4 | T7: 0 | U7: 2 | V7: 4 | W7: =MAX(0,ROUND(Q7/5*Weights!$B$3+R7/5*Weights!$B$4+S7/5*Weights!$B$5+T7/5*Weights!$B$6+U7/5*Weights!$B$7+V7/5*Weights!$B$8-L7*Weights!$B$9,0)) -> 72 | X7: =IF(W7>=Weights!$B$12,"A",IF(W7>=Weights!$B$13,"B","C")) -> A | Y7: Not contacted | Z7: Nate | AA7: Verify email (am@ vs alex@); find intro. | AB7: 2026-09-30 | AC7: https://www.radai.com/news/rad-ai-closes-50-million-to-empower-physicians-with-ai; https://www.khoslaventures.com/team/alex-morgan | AD7: Email inferred/unverified: am@khoslaventures.com (~61%) or alex@khoslaventures.com.
A8: DCVC Bio | B8: Computational-bio fund | C8: Palo Alto, CA | D8: DCVC Bio III, ~$700M+, 2024 | E8: Seed to early; computational biology (therapeutics-leaning) | F8: Unknown | G8: Selective | H8: No | I8: Computational/data-driven biology across drug development. Recent deals (Sidewinder, Radionetics, Latus Bio) lean therapeutics/deep-tech, not clinical software. | J8: Data/AI-native at the platform level; DCVC core (non-Bio) fund does more AI/data software. | K8: None competing directly with Foresight/iViz identified. | L8: 0 | M8: Unknown | N8: Kiersten Stead | O8: Managing Partner, DCVC Bio | P8: LinkedIn; consider a DCVC core partner for the software angle. No named node. | Q8: 5 | R8: 4 | S8: 3 | T8: 0 | U8: 2 | V8: 4 | W8: =MAX(0,ROUND(Q8/5*Weights!$B$3+R8/5*Weights!$B$4+S8/5*Weights!$B$5+T8/5*Weights!$B$6+U8/5*Weights!$B$7+V8/5*Weights!$B$8-L8*Weights!$B$9,0)) -> 70 | X8: =IF(W8>=Weights!$B$12,"A",IF(W8>=Weights!$B$13,"B","C")) -> A | Y8: Not contacted | Z8: Nate | AA8: Decide Bio vs core-fund partner; verify email. | AB8: 2026-09-30 | AC8: https://vcwire.tech/2024/10/01/dcvc-closes-over-700m-in-new-funds/; https://www.dcvc.com/team/kiersten-stead/ | AD8: Borderline Tier A; therapeutics lean makes a software seed less certain. Email inferred: kiersten@dcvc.com or kiersten.stead@dcvc.com.
A9: Menlo Ventures | B9: Multistage fund with bio+healthcare practice | C9: Menlo Park, CA | D9: Active flagship + Anthology (size/vintage not re-verified) | E9: Seed to growth; leads Series A/B more than seed | F9: Unknown | G9: Selective | H9: No | I9: Dedicated Bio+Healthcare practice; led $70M Series A in Chai Discovery (AI molecular design, 2025). | J9: Major AI thesis (early Anthropic backer); strong AI-native portfolio. | K9: Chai Discovery (AI drug design, not trial simulation). | L9: 0 | M9: Unknown | N9: Greg Yap | O9: Partner (life-science tech, digital health) | P9: Menlo LS portfolio CEO; no named node confirmed. | Q9: 4 | R9: 5 | S9: 3 | T9: 0 | U9: 2 | V9: 4 | W9: =MAX(0,ROUND(Q9/5*Weights!$B$3+R9/5*Weights!$B$4+S9/5*Weights!$B$5+T9/5*Weights!$B$6+U9/5*Weights!$B$7+V9/5*Weights!$B$8-L9*Weights!$B$9,0)) -> 68 | X9: =IF(W9>=Weights!$B$12,"A",IF(W9>=Weights!$B$13,"B","C")) -> B | Y9: Not contacted | Z9: Nate | AA9: Confirm seed appetite (they lean A); find intro to Yap. | AB9: 2026-09-30 | AC9: https://www.pharmexec.com/view/menlo-ventures-led-70-million-series-a-fundraiser-chai-discovery-transform-molecular-design; https://menlovc.com/team/greg-yap/ | AD9: Email inferred/unverified: greg@menlovc.com (~79%).
A10: 8VC | B10: Tech + life-sciences fund | C10: Austin / San Francisco | D10: Active multistage (size/vintage not re-verified) | E10: Pre-seed to Series A, leads; healthcare-data infrastructure | F10: Unknown | G10: Yes | H10: No | I10: Healthcare data-infrastructure and health-IT thesis; comfortable with enterprise health SaaS mapping to Coharts pharma/CRO buyers. | J10: AI named focus with portfolio evidence, not a pure AI-thesis fund. | K10: None competing directly with Foresight/iViz identified. | L10: 0 | M10: Unknown | N10: Kimmy Scotti | O10: Founding Partner (healthcare) | P10: LinkedIn or portfolio founder; no named node confirmed. | Q10: 4 | R10: 3 | S10: 4 | T10: 0 | U10: 2 | V10: 4 | W10: =MAX(0,ROUND(Q10/5*Weights!$B$3+R10/5*Weights!$B$4+S10/5*Weights!$B$5+T10/5*Weights!$B$6+U10/5*Weights!$B$7+V10/5*Weights!$B$8-L10*Weights!$B$9,0)) -> 64 | X10: =IF(W10>=Weights!$B$12,"A",IF(W10>=Weights!$B$13,"B","C")) -> B | Y10: Not contacted | Z10: Nate | AA10: Confirm a fresh clinical-software deal; verify email. | AB10: 2026-09-30 | AC10: https://signal.nfx.com/investors/kimmy-scotti; https://8vc.com/contact | AD10: Infra fit strengthens: enterprise health-data infrastructure / system-of-record is squarely 8VC's lane. Email inferred/unverified: kimmy@8vc.com (~76%). For enterprise clinical-data, 8VC bio team may co-fit.
A11: GV (Google Ventures) | B11: Corporate multistage fund | C11: Mountain View, CA | D11: Evergreen (Alphabet-backed) | E11: Seed to growth; life sciences and health co-led | F11: Unknown | G11: Selective | H11: No | I11: Physician-CS GP co-leads a deep life-sciences group; digital health, diagnostics, AI-in-healthcare (Flatiron, Verve incubation history). | J11: AI is a named focus with portfolio evidence across the firm. | K11: None competing directly with Foresight/iViz identified. | L11: 0 | M11: Unknown | N11: Krishna Yeshwant, MD | O11: Managing Partner / co-lead Life Sciences | P11: Portfolio founder or LinkedIn; no named node confirmed. | Q11: 5 | R11: 3 | S11: 3 | T11: 0 | U11: 2 | V11: 4 | W11: =MAX(0,ROUND(Q11/5*Weights!$B$3+R11/5*Weights!$B$4+S11/5*Weights!$B$5+T11/5*Weights!$B$6+U11/5*Weights!$B$7+V11/5*Weights!$B$8-L11*Weights!$B$9,0)) -> 66 | X11: =IF(W11>=Weights!$B$12,"A",IF(W11>=Weights!$B$13,"B","C")) -> B | Y11: Not contacted | Z11: Nate | AA11: Pull a 2025-26 LS deal to reference; verify email. | AB11: 2026-09-30 | AC11: https://www.gv.com/team/krishna-yeshwant; https://www.linkedin.com/in/kcyeshwant/ | AD11: Email inferred/unverified and low-confidence: krishna@gv.com (pattern first@ only ~37%, 8 formats).
A12: Breyer Capital | B12: Multistage fund building HC/LS practice | C12: Austin / Menlo Park | D12: Active (size/vintage not re-verified) | E12: Early-stage biomedical + AI; new healthcare mandate | F12: Unknown | G12: Selective | H12: No | I12: New, well-capitalized HC/LS mandate. Cheatham (hired Apr 2025) sourced Abridge and Hinge Health at Bessemer. | J12: Breyer is a longtime AI investor; Cheatham drives a healthcare-AI thesis. | K12: None competing directly with Foresight/iViz identified. | L12: 0 | M12: Unknown | N12: Morgan Cheatham, MD | O12: Partner and Head of Healthcare and Life Sciences | P12: LinkedIn; Cheatham runs public healthcare content, an engagement warm-up. No named node. | Q12: 3 | R12: 4 | S12: 3 | T12: 0 | U12: 2 | V12: 4 | W12: =MAX(0,ROUND(Q12/5*Weights!$B$3+R12/5*Weights!$B$4+S12/5*Weights!$B$5+T12/5*Weights!$B$6+U12/5*Weights!$B$7+V12/5*Weights!$B$8-L12*Weights!$B$9,0)) -> 58 | X12: =IF(W12>=Weights!$B$12,"A",IF(W12>=Weights!$B$13,"B","C")) -> B | Y12: Not contacted | Z12: Nate | AA12: Verify email via LinkedIn; confirm HC/LS check appetite. | AB12: 2026-09-30 | AC12: https://www.forbes.com/sites/sindhyavalloppillil/2025/04/24/billionaire-vc-jim-breyer-taps-morgan-cheatham-to-drive-the-future-of-healthcare-and-life-sciences/; https://www.linkedin.com/in/morgancheatham/ | AD12: Cheatham left Bessemer (Apr 2025). Email pattern unconfirmed; use LinkedIn.
A13: Obvious Ventures | B13: Seed/early world-positive fund | C13: San Francisco, CA | D13: Fund V, $360M, closed Jan 2026 | E13: Seed and Series A, leads; $5M to $12M checks | F13: $5M to $12M (per firm materials; confirm) | G13: Yes | H13: No | I13: Human-health theme with some bio/science holdings; not a dedicated bio fund. | J13: Responsible-AI theme with portfolio evidence. | K13: None competing directly with Foresight/iViz identified. | L13: 0 | M13: Unknown | N13: James Joaquin | O13: Co-Founder and Managing Director | P13: LinkedIn or portfolio founder; no named node confirmed. | Q13: 3 | R13: 3 | S13: 4 | T13: 5 | U13: 2 | V13: 5 | W13: =MAX(0,ROUND(Q13/5*Weights!$B$3+R13/5*Weights!$B$4+S13/5*Weights!$B$5+T13/5*Weights!$B$6+U13/5*Weights!$B$7+V13/5*Weights!$B$8-L13*Weights!$B$9,0)) -> 70 | X13: =IF(W13>=Weights!$B$12,"A",IF(W13>=Weights!$B$13,"B","C")) -> A | Y13: Not contacted | Z13: Nate | AA13: Verify email; confirm health-software recency. $5-12M checks lead a $6M seed cleanly. | AB13: 2026-09-30 | AC13: https://obvious.com/team/james-joaquin/; https://www.linkedin.com/in/jamesjoaquin | AD13: Check-size band published by the firm, so scored 3 rather than 0. Email inferred/unverified: james@obvious.com.
... A57: Care Equity | B57: Private equity (growth/control, life-science tools & services) | C57: New York, NY | D57: Care Equity II, $302M (Oct 2022); Fund I $125M (~$425M AUM) | E57: Growth/buyout PE; NOT venture seed | F57: Unknown (8-figure PE checks) | G57: No | H57: Yes (CRM: lead) | I57: Wet-lab / bioanalytics tools & services: OmicScouts (proteomics, exited to Momentum Mar 2025), TATAA Biocenter, Sapient Bioanalytics. | J57: None found; no AI/software-infrastructure holdings. | K57: None competing with Foresight/iViz; portfolio is lab services. | L57: 0 | M57: Unknown | N57: Sofia Etlin (firm: Peter Batesko, Founder/CEO) | O57: CRM contact | P57: Existing CRM contact (Sofia Etlin, lead stage); lighter than Oncology Ventures. Work directly if pursued. | Q57: 3 | R57: 1 | S57: 1 | T57: 1 | U57: 3 | V57: 4 | W57: =MAX(0,ROUND(Q57/5*Weights!$B$3+R57/5*Weights!$B$4+S57/5*Weights!$B$5+T57/5*Weights!$B$6+U57/5*Weights!$B$7+V57/5*Weights!$B$8-L57*Weights!$B$9,0)) -> 42 | X57: =IF(W57>=Weights!$B$12,"A",IF(W57>=Weights!$B$13,"B","C")) -> C | Y57: Not contacted | Z57: Nate | AA57: PASS: off-thesis PE (control in lab tools/services), wrong structure for a $6M software seed. | AB57: 2026-10-05 | AC57: https://pitchbook.com/profiles/investor/458093-80; https://www.privateequityinternational.com/institution-profiles/care-equity.html | AD57: Already in HubSpot (lead). Email sofia@careequity.com VERIFIED via CRM; firm head Peter Batesko (peter@careequity.com inferred). Off-thesis growth/control PE in life-science lab services.

Sheet Weights
A1: Scoring weights
A2: Dimension | B2: Weight | C2: Note
A3: Life science and TechBio evidence | B3: 30 | C3: Strongest predictor of a partner who can underwrite without a long education cycle.
A4: Applied AI thesis evidence | B4: 20 | C4: Written thesis or an AI-native portfolio, not a homepage mention.
A5: Stage fit | B5: 20 | C5: Scored against the confirmed round parameters, not a general notion of seed.
A6: Check size fit | B6: 10 | C6: Score 0 if unknown. Do not derive a check size from a fund size.
A7: Warm path strength | B7: 10 | C7: A named node scores high. An unnamed warm intro scores 2.
A8: Deployment activity | B8: 10 | C8: Dry powder and pace. Late-cycle funds take meetings and do not write.
A9: Conflict penalty (points) | B9: 25 | C9: Subtracted when Conflict flag is 1. Demotes rather than excludes.
A10: Total weight (should be 100) | B10: =SUM(B3:B8)
A12: Tier A threshold | B12: 70
A13: Tier B threshold | B13: 50
A15: Blue figures are editable levers.

Sheet Sources
A1: Firm | B1: Claim supported | C1: Source | D1: URL or record ID | E1: Accessed
A2: Dimension Capital | B2: Fund III $800M, Jul 2026, $1.65B AUM; Chai Discovery seed | C2: TechCrunch | D2: https://techcrunch.com/2026/07/21/dimension-capitals-800m-third-fund-shows-the-intersection-of-science-and-compute-is-booming/ | E2: 2026-07-27
A3: Dimension Capital | B3: Firm thesis and team | C3: Firm website | D3: https://www.dimensioncap.com/ | E3: 2026-07-27
A4: a16z Bio + Health | B4: AI-in-healthcare thesis and portfolio | C4: a16z | D4: https://a16z.com/infinite-healthcare-whats-it-worth/ | E4: 2026-07-27
A5: a16z Bio + Health | B5: Julie Yoo role | C5: a16z | D5: https://a16z.com/author/julie-yoo/ | E5: 2026-07-27
A6: Section 32 | B6: Pellini leads healthcare; Freenome/precision medicine | C6: Crunchbase | D6: https://www.crunchbase.com/person/michael-j-pellini | E6: 2026-07-27
A7: Lux Capital | B7: Shakir is a Lux GP, health/AI focus | C7: Firm website | D7: https://www.luxcapital.com/people | E7: 2026-07-27
A8: Foresite Capital | B8: Fund VI $900M Jun 2024; Xaira co-lead | C8: BioPharma Dive | D8: https://www.biopharmadive.com/news/foresite-950-million-fund-vi-venture-capital/718617/ | E8: 2026-07-27
A9: Khosla Ventures | B9: Khosla led Rad AI $50M Series B (2024) | C9: Rad AI | D9: https://www.radai.com/news/rad-ai-closes-50-million-to-empower-physicians-with-ai | E9: 2026-07-27
A10: DCVC Bio | B10: DCVC Bio III ~$700M, 2024 | C10: VCwire | D10: https://vcwire.tech/2024/10/01/dcvc-closes-over-700m-in-new-funds/ | E10: 2026-07-27
A11: Menlo Ventures | B11: Menlo led Chai Discovery $70M Series A (2025) | C11: PharmExec | D11: https://www.pharmexec.com/view/menlo-ventures-led-70-million-series-a-fundraiser-chai-discovery-transform-molecular-design | E11: 2026-07-27
A12: 8VC | B12: Scotti healthcare focus at 8VC | C12: Signal/NFX | D12: https://signal.nfx.com/investors/kimmy-scotti | E12: 2026-07-27
... A64: Care Equity | B64: Sofia Etlin CRM contact | C64: HubSpot CRM | D64: HubSpot company 348445133500 / contact 558213895894 | E64: 2026-10-05
